<annotation>
	<folder>Andy</folder>
	<filename>03170037_0394.jpg</filename>
	<path>C:\Users\17654\Box\vip-vaa-spring2023\Images to Label\Andy\03170037_0394.jpg</path>
	<source>
		<database>Unknown</database>
	</source>
	<size>
		<width>1280</width>
		<height>720</height>
		<depth>3</depth>
	</size>
	<segmented>0</segmented>
	<object>
		<name>1</name>
		<pose>Unspecified</pose>
		<truncated>0</truncated>
		<difficult>0</difficult>
		<bndbox>
			<xmin>838</xmin>
			<ymin>133</ymin>
			<xmax>952</xmax>
			<ymax>278</ymax>
		</bndbox>
	</object>
	<object>
		<name>1</name>
		<pose>Unspecified</pose>
		<truncated>0</truncated>
		<difficult>0</difficult>
		<bndbox>
			<xmin>1098</xmin>
			<ymin>172</ymin>
			<xmax>1158</xmax>
			<ymax>240</ymax>
		</bndbox>
	</object>
	<object>
		<name>1</name>
		<pose>Unspecified</pose>
		<truncated>0</truncated>
		<difficult>0</difficult>
		<bndbox>
			<xmin>1175</xmin>
			<ymin>171</ymin>
			<xmax>1246</xmax>
			<ymax>258</ymax>
		</bndbox>
	</object>
</annotation>
